{
  "version": "6",
  "dialect": "postgresql",
  "entries": [
    {
      "idx": 0,
      "version": "6",
      "when": 1731265897992,
      "tag": "0000_classy_microchip",
      "breakpoints": true
    },
    {
      "idx": 1,
      "version": "6",
      "when": 1731266141252,
      "tag": "0001_fair_texas_twister",
      "breakpoints": true
    },
    {
      "idx": 2,
      "version": "6",
      "when": 1731351009070,
      "tag": "0002_legal_centennial",
      "breakpoints": true
    }
  ]
}